openapi_to_asciidoc/__init__.py
openapi_to_asciidoc/convert.py
openapi_to_asciidoc/objects.py
openapi_to_asciidoc/render.py
openapi_to_asciidoc/templates/callback_obj.j2
openapi_to_asciidoc/templates/components_obj.j2
openapi_to_asciidoc/templates/contact_obj.j2
openapi_to_asciidoc/templates/discriminator_obj.j2
openapi_to_asciidoc/templates/encoding_obj.j2
openapi_to_asciidoc/templates/example_obj.j2
openapi_to_asciidoc/templates/external_docs_obj.j2
openapi_to_asciidoc/templates/header_obj.j2
openapi_to_asciidoc/templates/info_obj.j2
openapi_to_asciidoc/templates/license_obj.j2
openapi_to_asciidoc/templates/link_obj.j2
openapi_to_asciidoc/templates/media_type_obj.j2
openapi_to_asciidoc/templates/oauth_flow_obj.j2
openapi_to_asciidoc/templates/oauth_flows_obj.j2
openapi_to_asciidoc/templates/openapi_obj.j2
openapi_to_asciidoc/templates/operation_obj.j2
openapi_to_asciidoc/templates/parameter_obj.j2
openapi_to_asciidoc/templates/path_item_obj.j2
openapi_to_asciidoc/templates/paths_obj.j2
openapi_to_asciidoc/templates/request_body_obj.j2
openapi_to_asciidoc/templates/response_obj.j2
openapi_to_asciidoc/templates/schema_obj.j2
openapi_to_asciidoc/templates/security_requirement_obj.j2
openapi_to_asciidoc/templates/security_scheme_obj.j2
openapi_to_asciidoc/templates/server_obj.j2
openapi_to_asciidoc/templates/server_variable_obj.j2
openapi_to_asciidoc/templates/specification_extension.j2
openapi_to_asciidoc/templates/tag_obj.j2
openapi_to_asciidoc/templates/util.j2
openapi_to_asciidoc/templates/xml_obj.j2
openapi_to_asciidoc-0.1.4.dist-info/METADATA
openapi_to_asciidoc-0.1.4.dist-info/WHEEL
openapi_to_asciidoc-0.1.4.dist-info/entry_points.txt
openapi_to_asciidoc-0.1.4.dist-info/licenses/LICENSE
openapi_to_asciidoc-0.1.4.dist-info/RECORD
