Metadata-Version: 2.1
Name: openapi-to-asciidoc
Version: 0.1.4
Summary: A tool used to convert OpenAPI 3.1 specifications to AsciiDoc
Author-email: LFV <info@lfv.se>
License-File: LICENSE
Classifier: Development Status :: 4 - Beta
Classifier: Intended Audience :: Developers
Classifier: License :: OSI Approved :: MIT License
Classifier: Operating System :: OS Independent
Classifier: Programming Language :: Python :: 3.10
Classifier: Programming Language :: Python :: 3.11
Classifier: Programming Language :: Python :: 3.12
Classifier: Topic :: Software Development :: Build Tools
Requires-Python: >=3.10
Requires-Dist: jinja2-cli>=0.8.2
Requires-Dist: jinja2>=3.1.2
Requires-Dist: marshmallow>=3.19.0
